finavis/__init__.py
finavis/core/__init__.py
finavis/core/quote.py
finavis/core/screener.py
finavis/exceptions.py
finavis/library/__init__.py
finavis/library/enums.py
finavis/library/models.py
finavis/library/types.py
finavis/utils/__init__.py
finavis/utils/functions.py
finavis/utils/sessions.py
finavis-0.0.37.dist-info/LICENSE
finavis-0.0.37.dist-info/METADATA
finavis-0.0.37.dist-info/WHEEL
finavis-0.0.37.dist-info/RECORD
