Metadata-Version: 2.1
Name: finavis
Version: 0.0.37
Summary: another unofficial api for some financial visualization website
Home-page: https://github.com/rdnve/finavis
License: MIT
Keywords: finance,datascience,scrapper,markets,stock,quote,ticker,finviz
Author: serje ù
Author-email: pleaseanswermeserjeu@icloud.com
Requires-Python: >=3.12,<3.13
Classifier: Development Status :: 3 - Alpha
Classifier: Environment :: Web Environment
Classifier: Intended Audience :: Developers
Classifier: License :: OSI Approved :: MIT License
Classifier: Natural Language :: English
Classifier: Operating System :: OS Independent
Classifier: Programming Language :: Python :: 3
Classifier: Programming Language :: Python :: 3.12
Classifier: Topic :: Internet :: WWW/HTTP
Classifier: Topic :: Software Development :: Libraries
Requires-Dist: attrs (>=23.2,<23.3)
Requires-Dist: cssselect (>=1.2,<1.3)
Requires-Dist: lxml (>=4,<5)
Requires-Dist: requests[socks] (>=2.32,<2.33)
Requires-Dist: user-agent (>=0.1,<0.2)
Project-URL: Repository, https://github.com/rdnve/finavis
